bin_waterfall/__init__.py
bin_waterfall/binWaterFallclass.py
bin_waterfall-0.1.0.dist-info/METADATA
bin_waterfall-0.1.0.dist-info/WHEEL
bin_waterfall-0.1.0.dist-info/top_level.txt
bin_waterfall-0.1.0.dist-info/RECORD
