Metadata-Version: 2.4
Name: bin-waterfall
Version: 0.1.0
Summary: A Python library for waterfall chart generation
Author-email: Your Name <your@email.com>
License: MIT
Requires-Python: >=3.8
Requires-Dist: numpy>=1.25
Requires-Dist: scipy>=1.10
Requires-Dist: matplotlib>=3.5
